bwi/__init__.py
bwi/_internal_logging.py
bwi/_queue_sender.py
bwi/logs.py
bwi/metrics.py
bwi-0.1.2.dist-info/METADATA
bwi-0.1.2.dist-info/WHEEL
bwi-0.1.2.dist-info/top_level.txt
bwi-0.1.2.dist-info/RECORD
