Metadata-Version: 2.1
Name: bwi
Version: 0.1.2
Summary: Package to add bwi methods into your project
Home-page: https://gitlab.com/bwi-gpe/bwi-lib
Author: BWI
Author-email: contact@bwi-project.com
License: UNKNOWN
Platform: UNKNOWN
Requires-Python: >=3.0
